ksbanim.py
ksbanim-1.2.20.dist-info/METADATA
ksbanim-1.2.20.dist-info/WHEEL
ksbanim-1.2.20.dist-info/top_level.txt
ksbanim-1.2.20.dist-info/RECORD
