Metadata-Version: 2.4
Name: ksbanim
Version: 1.2.20
Summary: A module for animation based on PyQt5 and OpenGL
Home-page: https://github.com/tunnelrind/ksbanim
Author: Biasini Dario
Author-email: tunnelrind@lernbaum.ch
License: MIT
Classifier: Programming Language :: Python :: 3
Classifier: Operating System :: OS Independent
Requires-Python: >=3.6
Requires-Dist: PyQt5
Requires-Dist: PyOpenGL
Requires-Dist: imageio[ffmpeg]
Requires-Dist: requests
Dynamic: author
Dynamic: author-email
Dynamic: classifier
Dynamic: description
Dynamic: description-content-type
Dynamic: home-page
Dynamic: license
Dynamic: requires-dist
Dynamic: requires-python
Dynamic: summary
